Metadata-Version: 2.4
Name: livekit-agents-irontec
Version: 1.1.5
Summary: A powerful framework for building realtime voice AI agents
Project-URL: Documentation, https://docs.livekit.io
Project-URL: Website, https://livekit.io/
Project-URL: Source, https://github.com/livekit/agents
Author-email: LiveKit <hello@livekit.io>
License-Expression: Apache-2.0
Keywords: AI,agents,audio,livekit,realtime,video,webrtc
Classifier: Intended Audience :: Developers
Classifier: License :: OSI Approved :: Apache Software License
Classifier: Programming Language :: Python :: 3
Classifier: Programming Language :: Python :: 3 :: Only
Classifier: Programming Language :: Python :: 3.9
Classifier: Programming Language :: Python :: 3.10
Classifier: Topic :: Multimedia :: Sound/Audio
Classifier: Topic :: Multimedia :: Video
Classifier: Topic :: Scientific/Engineering :: Artificial Intelligence
Requires-Python: >=3.9
Requires-Dist: aiohttp~=3.10
Requires-Dist: av>=12.0.0
Requires-Dist: click~=8.1
Requires-Dist: colorama>=0.4.6
Requires-Dist: docstring-parser>=0.16
Requires-Dist: eval-type-backport
Requires-Dist: livekit-api-irontec
Requires-Dist: livekit-irontec
Requires-Dist: livekit-protocol-irontec~=1.0
Requires-Dist: nest-asyncio>=1.6.0
Requires-Dist: numpy>=1.26.0
Requires-Dist: protobuf>=3
Requires-Dist: psutil>=7.0
Requires-Dist: pydantic<3,>=2.0
Requires-Dist: pyjwt>=2.0
Requires-Dist: sounddevice>=0.5
Requires-Dist: types-protobuf<5,>=4
Requires-Dist: typing-extensions>=4.12
Requires-Dist: watchfiles>=1.0
Provides-Extra: anthropic
Requires-Dist: livekit-plugins-anthropic>=1.1.5; extra == 'anthropic'
Provides-Extra: assemblyai
Requires-Dist: livekit-plugins-assemblyai>=1.1.5; extra == 'assemblyai'
Provides-Extra: aws
Requires-Dist: livekit-plugins-aws>=1.1.5; extra == 'aws'
Provides-Extra: azure
Requires-Dist: livekit-plugins-azure>=1.1.5; extra == 'azure'
Provides-Extra: baseten
Requires-Dist: livekit-plugins-baseten>=1.1.5; extra == 'baseten'
Provides-Extra: bey
Requires-Dist: livekit-plugins-bey>=1.1.5; extra == 'bey'
Provides-Extra: bithuman
Requires-Dist: livekit-plugins-bithuman>=1.1.5; extra == 'bithuman'
Provides-Extra: cartesia
Requires-Dist: livekit-plugins-cartesia>=1.1.5; extra == 'cartesia'
Provides-Extra: clova
Requires-Dist: livekit-plugins-clova>=1.1.5; extra == 'clova'
Provides-Extra: codecs
Requires-Dist: av>=12.0.0; extra == 'codecs'
Requires-Dist: numpy>=1.26.0; extra == 'codecs'
Provides-Extra: deepgram
Requires-Dist: livekit-plugins-deepgram>=1.1.5; extra == 'deepgram'
Provides-Extra: elevenlabs
Requires-Dist: livekit-plugins-elevenlabs>=1.1.5; extra == 'elevenlabs'
Provides-Extra: fal
Requires-Dist: livekit-plugins-fal>=1.1.5; extra == 'fal'
Provides-Extra: gladia
Requires-Dist: livekit-plugins-gladia>=1.1.5; extra == 'gladia'
Provides-Extra: google
Requires-Dist: livekit-plugins-google>=1.1.5; extra == 'google'
Provides-Extra: groq
Requires-Dist: livekit-plugins-groq>=1.1.5; extra == 'groq'
Provides-Extra: hedra
Requires-Dist: livekit-plugins-hedra>=1.1.5; extra == 'hedra'
Provides-Extra: hume
Requires-Dist: livekit-plugins-hume>=1.1.5; extra == 'hume'
Provides-Extra: images
Requires-Dist: pillow>=10.3.0; extra == 'images'
Provides-Extra: inworld
Requires-Dist: livekit-plugins-inworld>=1.1.5; extra == 'inworld'
Provides-Extra: langchain
Requires-Dist: livekit-plugins-langchain>=1.1.5; extra == 'langchain'
Provides-Extra: lmnt
Requires-Dist: livekit-plugins-lmnt>=1.1.5; extra == 'lmnt'
Provides-Extra: mcp
Requires-Dist: mcp<2,>=1.6.0; (python_version >= '3.10') and extra == 'mcp'
Provides-Extra: neuphonic
Requires-Dist: livekit-plugins-neuphonic>=1.1.5; extra == 'neuphonic'
Provides-Extra: nltk
Requires-Dist: livekit-plugins-nltk>=1.1.5; extra == 'nltk'
Provides-Extra: openai
Requires-Dist: livekit-plugins-openai>=1.1.5; extra == 'openai'
Provides-Extra: playai
Requires-Dist: livekit-plugins-playai>=1.1.5; extra == 'playai'
Provides-Extra: resemble
Requires-Dist: livekit-plugins-resemble>=1.1.5; extra == 'resemble'
Provides-Extra: rime
Requires-Dist: livekit-plugins-rime>=1.1.5; extra == 'rime'
Provides-Extra: sarvam
Requires-Dist: livekit-plugins-sarvam>=1.1.5; extra == 'sarvam'
Provides-Extra: silero
Requires-Dist: livekit-plugins-silero>=1.1.5; extra == 'silero'
Provides-Extra: speechify
Requires-Dist: livekit-plugins-speechify>=1.1.5; extra == 'speechify'
Provides-Extra: speechmatics
Requires-Dist: livekit-plugins-speechmatics>=1.1.5; extra == 'speechmatics'
Provides-Extra: spitch
Requires-Dist: livekit-plugins-spitch>=1.1.5; extra == 'spitch'
Provides-Extra: tavus
Requires-Dist: livekit-plugins-tavus>=1.1.5; extra == 'tavus'
Provides-Extra: turn-detector
Requires-Dist: livekit-plugins-turn-detector>=1.1.5; extra == 'turn-detector'
